awsmc/__init__.py
awsmc/__main__.py
awsmc/ami.py
awsmc/cli.py
awsmc/exc.py
awsmc/server.py
awsmc/spigot.py
awsmc/util.py
awsmc-0.0.10.dist-info/DESCRIPTION.rst
awsmc-0.0.10.dist-info/METADATA
awsmc-0.0.10.dist-info/RECORD
awsmc-0.0.10.dist-info/WHEEL
awsmc-0.0.10.dist-info/entry_points.txt
awsmc-0.0.10.dist-info/metadata.json
awsmc-0.0.10.dist-info/top_level.txt
