Metadata-Version: 2.0
Name: awsmc
Version: 0.0.10
Summary: Simple and cheap minecraft hosting on AWS
Home-page: https://github.com/brenns10/awsmc
Author: Stephen Brennan
Author-email: stephen@brennan.io
License: Revised BSD
Keywords: AWS minecraft
Platform: UNKNOWN
Classifier: Programming Language :: Python :: 3
Classifier: License :: OSI Approved :: BSD License
Classifier: Development Status :: 4 - Beta
Requires-Dist: paramiko
Requires-Dist: requests
Requires-Dist: screenutils
Requires-Dist: boto3
Requires-Dist: python-crontab
